{"inkVersion":18,"root":[[{"->":"intro"},["done",{"#f":7,"#n":"g-0"}],null],"done",{"intro":[{"#":"location: camp"},"^Summer. The most exciting time of the year. ",{"#":"thought"},"\n","^Yeah right. ",{"#":"thought"},"\n","^All the years before I just got to hang out with all my friends at home. Playing video games and eating pizza and having good old fashioned kid fun. ",{"#":"thought"},"\n","^But no. This year is different. ",{"#":"thought"},"\n","^My parents decided that I getting some outdoor time would be good for me. ",{"#":"thought"},"\n","^Plus they wanted to go to Europe. ",{"#":"thought"},"\n","^So here I am on my way to Camp Fruit. ",{"#":"thought"},"\n",{"->":"arrive_at_camp"},{"#f":3}],"arrive_at_camp":[[{"#":"location: camp"},"^The bus pulls up.","\n","^A gate on the road reads \"Camp Fruit! Where all your dreams come true!\"","\n","^Counselor: \"Okay everyone! Get all your belongings and let's hike up to the cabin!\"","\n","^Why is everything so chipper here? ",{"#":"thought"},"\n","ev","str","^It's probably the trees.","/str","/ev",{"*":".^.c-0","flg":20},"ev","str","^Who knows?","/str","/ev",{"*":".^.c-1","flg":20},{"c-0":["^ ",{"->":".^.^.^.move_on"},"\n",{"#f":7}],"c-1":["^ ",{"->":".^.^.^.move_on"},"\n",{"#f":7}]}],{"move_on":["^Well, let's go. ",{"#":"thought"},"\n","^Counselor: \"Hey, there's this person that wants to talk to you over by the picnic tables.\"","\n","^Counselor: \"Clearly you two should be friends!\"","\n",{"->":"picnic"},{"#f":3}],"#f":3}],"picnic":[{"#":"location: picnic"},"^Oh no, it's your soon-to-be rival!","\n","^And they want to d-d-d-d-d-d-d-duel!","\n","end",{"#f":3}],"#f":3}],"listDefs":{}}